ukrainian_tts/__init__.py
ukrainian_tts/formatter.py
ukrainian_tts/stress.py
ukrainian_tts/tts.py
ukrainian_tts/vendor/__init__.py
ukrainian_tts/vendor/accentor-lite.pt
ukrainian_tts/vendor/ukrainian_accentor.py
ukrainian_tts-6.0.2.dist-info/licenses/LICENSE
ukrainian_tts-6.0.2.dist-info/METADATA
ukrainian_tts-6.0.2.dist-info/WHEEL
ukrainian_tts-6.0.2.dist-info/top_level.txt
ukrainian_tts-6.0.2.dist-info/RECORD
