Metadata-Version: 2.4
Name: ukrainian-tts
Version: 6.0.2
Summary: Ukrainian TTS using ESPNET
Home-page: https://github.com/robinhad/ukrainian-tts
Author: Yurii Paniv
Author-email: Yurii Paniv <mr.robinhad@gmail.com>
License: MIT
Project-URL: Homepage, https://github.com/robinhad/ukrainian-tts
Project-URL: Repository, https://github.com/robinhad/ukrainian-tts
Project-URL: Issues, https://github.com/robinhad/ukrainian-tts/issues
Classifier: Development Status :: 4 - Beta
Classifier: Intended Audience :: Developers
Classifier: License :: OSI Approved :: MIT License
Classifier: Programming Language :: Python :: 3
Classifier: Programming Language :: Python :: 3.8
Classifier: Programming Language :: Python :: 3.9
Classifier: Programming Language :: Python :: 3.10
Classifier: Programming Language :: Python :: 3.11
Classifier: Programming Language :: Python :: 3.12
Classifier: Programming Language :: Python :: 3.13
Requires-Python: >3.6.0
License-File: LICENSE
Requires-Dist: torch>=2.8.0
Requires-Dist: torchaudio>=2.8.0
Requires-Dist: espnet==202509
Requires-Dist: typeguard<5.0,>=4.4.0
Requires-Dist: num2words>=0.5.12
Requires-Dist: ukrainian-word-stress==1.1.0
Requires-Dist: scipy<2.0.0,>=1.16.0
Requires-Dist: gradio>=5.47.0
Requires-Dist: huggingface_hub>=0.35.0
Requires-Dist: sentencepiece>=0.2.0
Requires-Dist: soundfile>=0.13.0
Requires-Dist: librosa>=0.11.0
Requires-Dist: kaldiio>=2.18.0
Requires-Dist: stanza>=1.10.0
Requires-Dist: numpy>=2.3.0
Requires-Dist: requests>=2.32.0
Requires-Dist: espnet-tts-frontend>=0.0.3
Requires-Dist: torch-complex>=0.4.4
Requires-Dist: torchmetrics>=1.8.0
Requires-Dist: pytorch-lightning>=2.5.0
Provides-Extra: dev
Requires-Dist: pytest; extra == "dev"
Requires-Dist: pytest-cov; extra == "dev"
Requires-Dist: black; extra == "dev"
Requires-Dist: flake8; extra == "dev"
Requires-Dist: mypy; extra == "dev"
Dynamic: author
Dynamic: home-page
Dynamic: license-file
Dynamic: requires-python
